setup.py
bin/blockstack
blockstack_client/__init__.py
blockstack_client/accounts.py
blockstack_client/actions.py
blockstack_client/app.py
blockstack_client/b40.py
blockstack_client/cli.py
blockstack_client/client.py
blockstack_client/config.py
blockstack_client/data.py
blockstack_client/keys.py
blockstack_client/method_parser.py
blockstack_client/profile.py
blockstack_client/proxy.py
blockstack_client/rpc.py
blockstack_client/rpc_runner.py
blockstack_client/scripts.py
blockstack_client/snv.py
blockstack_client/storage.py
blockstack_client/tx.py
blockstack_client/user.py
blockstack_client/utils.py
blockstack_client/version.py
blockstack_client/wallet.py
blockstack_client.egg-info/PKG-INFO
blockstack_client.egg-info/SOURCES.txt
blockstack_client.egg-info/dependency_links.txt
blockstack_client.egg-info/not-zip-safe
blockstack_client.egg-info/requires.txt
blockstack_client.egg-info/top_level.txt
blockstack_client/backend/__init__.py
blockstack_client/backend/blockchain.py
blockstack_client/backend/nameops.py
blockstack_client/backend/queue.py
blockstack_client/backend/registrar.py
blockstack_client/backend/crypto/__init__.py
blockstack_client/backend/crypto/bip38.py
blockstack_client/backend/crypto/utils.py
blockstack_client/backend/drivers/__init__.py
blockstack_client/backend/drivers/blockstack_resolver.py
blockstack_client/backend/drivers/blockstack_server.py
blockstack_client/backend/drivers/common.py
blockstack_client/backend/drivers/dht.py
blockstack_client/backend/drivers/disk.py
blockstack_client/backend/drivers/http.py
blockstack_client/backend/drivers/s3.py
blockstack_client/backend/utxo/__init__.py
blockstack_client/backend/utxo/blockstack_utxo.py
blockstack_client/backend/utxo/utxo.py
blockstack_client/operations/__init__.py
blockstack_client/operations/announce.py
blockstack_client/operations/nameimport.py
blockstack_client/operations/namespacepreorder.py
blockstack_client/operations/namespaceready.py
blockstack_client/operations/namespacereveal.py
blockstack_client/operations/preorder.py
blockstack_client/operations/register.py
blockstack_client/operations/revoke.py
blockstack_client/operations/transfer.py
blockstack_client/operations/update.py