Metadata-Version: 1.1
Name: blockstack-client
Version: 0.14.0.6
Summary: Python client library for Blockstack
Home-page: https://github.com/blockstack/blockstack-client
Author: Blockstack.org
Author-email: support@blockstack.org
License: GPLv3
Download-URL: https://github.com/blockstack/blockstack-cli/archive/master.zip
Keywords: blockchain bitcoin btc cryptocurrency name key value store data
Platform: UNKNOWN
Classifier: Intended Audience :: Developers
Classifier: License :: OSI Approved :: GNU General Public License v3 (GPLv3)
Classifier: Operating System :: OS Independent
Classifier: Programming Language :: Python :: 2 :: Only
Classifier: Topic :: Internet
Classifier: Topic :: Security :: Cryptography
Classifier: Topic :: Software Development :: Libraries :: Python Modules
